ImageEnhancer/__init__.py
ImageEnhancer/inference_realesrgan.py
ImageEnhancer-1.0.dist-info/LICENSE
ImageEnhancer-1.0.dist-info/METADATA
ImageEnhancer-1.0.dist-info/WHEEL
ImageEnhancer-1.0.dist-info/top_level.txt
ImageEnhancer-1.0.dist-info/RECORD
